[{"otakotaku": 2365, "title": "\"Oshi no Ko\"", "myanimelist": null, "animeplanet": null, "anidb": null, "animenewsnetwork": null}, {"otakotaku": 2781, "title": "\"Oshi no Ko\" Season 2", "myanimelist": null, "animeplanet": null, "anidb": null, "animenewsnetwork": null}, {"otakotaku": 1651, "title": "22/7", "myanimelist": null, "animeplanet": null, "anidb": null, "animenewsnetwork": null}, {"otakotaku": 2369, "title": "5-Oku-Nen Button", "myanimelist": null, "animeplanet": null, "anidb": null, "animenewsnetwork": null}, {"otakotaku": 2876, "title": "5-toubun no Hanayome*", "myanimelist": null, "animeplanet": null, "anidb": null, "animenewsnetwork": null}, {"otakotaku": 1729, "title": "7 Seeds Season 2", "myanimelist": null, "animeplanet": null, "anidb": null, "animenewsnetwork": null}, {"otakotaku": 1748, "title": "86", "myanimelist": null, "animeplanet": null, "anidb": null, "animenewsnetwork": null}, {"otakotaku": 1995, "title": "86 Part 2", "myanimelist": null, "animeplanet": null, "anidb": null, "animenewsnetwork": null}, {"otakotaku": 527, "title": "Ajin Part 2", "myanimelist": null, "animeplanet": null, "anidb": null, "animenewsnetwork": null}, {"otakotaku": 195, "title": "Aldnoah.Zero", "myanimelist": null, "animeplanet": null, "anidb": null, "animenewsnetwork": null}, {"otakotaku": 196, "title": "Aldnoah.Zero 2nd Season", "myanimelist": null, "animeplanet": null, "anidb": null, "animenewsnetwork": null}, {"otakotaku": 2398, "title": "Alice Gear Aegis Expansion", "myanimelist": null, "animeplanet": null, "anidb": null, "animenewsnetwork": null}, {"otakotaku": 558, "title": "All Out!!", "myanimelist": null, "animeplanet": null, "anidb": null, "animenewsnetwork": null}, {"otakotaku": 517, "title": "Amagi Brilliant Park: Nonbirishiteiru Hima ga Nai!", "myanimelist": null, "animeplanet": null, "anidb": null, "animenewsnetwork": null}, {"otakotaku": 1337, "title": "Amnesia", "myanimelist": null, "animeplanet": null, "anidb": null, "animenewsnetwork": null}, {"otakotaku": 2345, "title": "Angel Dives", "myanimelist": null, "animeplanet": null, "anidb": null, "animenewsnetwork": null}, {"otakotaku": 1174, "title": "Ani ni Tsukeru Kusuri wa Nai!", "myanimelist": null, "animeplanet": null, "anidb": null, "animenewsnetwork": null}, {"otakotaku": 1175, "title": "Ani ni Tsukeru Kusuri wa Nai! 2", "myanimelist": null, "animeplanet": null, "anidb": null, "animenewsnetwork": null}, {"otakotaku": 1665, "title": "Ani ni Tsukeru Kusuri wa Nai! 3", "myanimelist": null, "animeplanet": null, "anidb": null, "animenewsnetwork": null}, {"otakotaku": 332, "title": "Anne Happy\u266a", "myanimelist": null, "animeplanet": null, "anidb": null, "animenewsnetwork": null}, {"otakotaku": 2110, "title": "Ao Ashi", "myanimelist": null, "animeplanet": null, "anidb": null, "animenewsnetwork": null}, {"otakotaku": 1953, "title": "Aoi Hane Mitsuketa! Sagashite Miyou Mijika na Tori-tachi", "myanimelist": null, "animeplanet": null, "anidb": null, "animenewsnetwork": null}, {"otakotaku": 1706, "title": "Appare-Ranman!", "myanimelist": null, "animeplanet": null, "anidb": null, "animenewsnetwork": null}, {"otakotaku": 1723, "title": "Argonavis from BanG Dream!", "myanimelist": null, "animeplanet": null, "anidb": null, "animenewsnetwork": null}, {"otakotaku": 1401, "title": "Aria The Animation", "myanimelist": null, "animeplanet": null, "anidb": null, "animenewsnetwork": null}, {"otakotaku": 1408, "title": "Aria The Natural", "myanimelist": null, "animeplanet": null, "anidb": null, "animenewsnetwork": null}, {"otakotaku": 1607, "title": "Aria The Origination", "myanimelist": null, "animeplanet": null, "anidb": null, "animenewsnetwork": null}, {"otakotaku": 2028, "title": "Aria the Avvenire", "myanimelist": null, "animeplanet": null, "anidb": null, "animenewsnetwork": null}, {"otakotaku": 2029, "title": "Aria the Benedizione", "myanimelist": null, "animeplanet": null, "anidb": null, "animenewsnetwork": null}, {"otakotaku": 1986, "title": "Aria the Crepuscolo", "myanimelist": null, "animeplanet": null, "anidb": null, "animenewsnetwork": null}, {"otakotaku": 1662, "title": "Arifureta Shokugyou de Sekai Saikyou Season 2", "myanimelist": null, "animeplanet": null, "anidb": null, "animenewsnetwork": null}, {"otakotaku": 2641, "title": "Arknights: Fuyukomori Kaerimichi", "myanimelist": null, "animeplanet": null, "anidb": null, "animenewsnetwork": null}, {"otakotaku": 774, "title": "Armed Blue: Gunvolt", "myanimelist": null, "animeplanet": null, "anidb": null, "animenewsnetwork": null}, {"otakotaku": 1585, "title": "Assassins Pride", "myanimelist": null, "animeplanet": null, "anidb": null, "animenewsnetwork": null}, {"otakotaku": 1693, "title": "Assault Lily: Bouquet", "myanimelist": null, "animeplanet": null, "anidb": null, "animenewsnetwork": null}, {"otakotaku": 2791, "title": "Atri: My Dear Moments", "myanimelist": null, "animeplanet": null, "anidb": null, "animenewsnetwork": null}, {"otakotaku": 2572, "title": "Ayaka", "myanimelist": null, "animeplanet": null, "anidb": null, "animenewsnetwork": null}, {"otakotaku": 1545, "title": "Azur Lane", "myanimelist": null, "animeplanet": null, "anidb": null, "animenewsnetwork": null}, {"otakotaku": 468, "title": "B-Project: Kodou*Ambitious", "myanimelist": null, "animeplanet": null, "anidb": null, "animenewsnetwork": null}, {"otakotaku": 2638, "title": "B-Project: Netsuretsu*Love Call", "myanimelist": null, "animeplanet": null, "anidb": null, "animenewsnetwork": null}, {"otakotaku": 1415, "title": "B-Project: Zecchou*Emotion", "myanimelist": null, "animeplanet": null, "anidb": null, "animenewsnetwork": null}, {"otakotaku": 1595, "title": "Babylon", "myanimelist": null, "animeplanet": null, "anidb": null, "animenewsnetwork": null}, {"otakotaku": 1832, "title": "Back Arrow", "myanimelist": null, "animeplanet": null, "anidb": null, "animenewsnetwork": null}, {"otakotaku": 1097, "title": "Baki", "myanimelist": null, "animeplanet": null, "anidb": null, "animenewsnetwork": null}, {"otakotaku": 1164, "title": "BanG Dream! Season 2", "myanimelist": null, "animeplanet": null, "anidb": null, "animenewsnetwork": null}, {"otakotaku": 1094, "title": "Banana Fish", "myanimelist": null, "animeplanet": null, "anidb": null, "animenewsnetwork": null}, {"otakotaku": 2273, "title": "Bastard!! Ankoku no Hakaishin (ONA)", "myanimelist": null, "animeplanet": null, "anidb": null, "animenewsnetwork": null}, {"otakotaku": 2601, "title": "Bastard!! Ankoku no Hakaishin Part 2 (ONA)", "myanimelist": null, "animeplanet": null, "anidb": null, "animenewsnetwork": null}, {"otakotaku": 2602, "title": "Bastard!! Ankoku no Hakaishin Season 2 (ONA)", "myanimelist": null, "animeplanet": null, "anidb": null, "animenewsnetwork": null}, {"otakotaku": 1537, "title": "Beastars", "myanimelist": null, "animeplanet": null, "anidb": null, "animenewsnetwork": null}, {"otakotaku": 2844, "title": "Beastars Final Season", "myanimelist": null, "animeplanet": null, "anidb": null, "animenewsnetwork": null}, {"otakotaku": 1834, "title": "Beastars Season 2", "myanimelist": null, "animeplanet": null, "anidb": null, "animenewsnetwork": null}, {"otakotaku": 964, "title": "Beatless", "myanimelist": null, "animeplanet": null, "anidb": null, "animenewsnetwork": null}, {"otakotaku": 1272, "title": "Beatless Final Stage", "myanimelist": null, "animeplanet": null, "anidb": null, "animenewsnetwork": null}, {"otakotaku": 1486, "title": "Bem", "myanimelist": null, "animeplanet": null, "anidb": null, "animenewsnetwork": null}, {"otakotaku": 353, "title": "Berserk", "myanimelist": null, "animeplanet": null, "anidb": null, "animenewsnetwork": null}, {"otakotaku": 2462, "title": "Berserk: Ougon Jidai-hen - Memorial Edition", "myanimelist": null, "animeplanet": null, "anidb": null, "animenewsnetwork": null}, {"otakotaku": 1535, "title": "Beyblade Burst Gachi", "myanimelist": null, "animeplanet": null, "anidb": null, "animenewsnetwork": null}, {"otakotaku": 266, "title": "Big Order", "myanimelist": null, "animeplanet": null, "anidb": null, "animenewsnetwork": null}, {"otakotaku": 265, "title": "Big Order OVA", "myanimelist": null, "animeplanet": null, "anidb": null, "animenewsnetwork": null}, {"otakotaku": 2109, "title": "Birdie Wing: Golf Girls' Story", "myanimelist": null, "animeplanet": null, "anidb": null, "animenewsnetwork": null}, {"otakotaku": 2507, "title": "Birdie Wing: Golf Girls' Story Season 2", "myanimelist": null, "animeplanet": null, "anidb": null, "animenewsnetwork": null}, {"otakotaku": 1380, "title": "Black Fox", "myanimelist": null, "animeplanet": null, "anidb": null, "animenewsnetwork": null}, {"otakotaku": 2080, "title": "Black\u2605\u2605Rock Shooter: Dawn Fall", "myanimelist": null, "animeplanet": null, "anidb": null, "animenewsnetwork": null}, {"otakotaku": 2233, "title": "Bleach: Sennen Kessen-hen", "myanimelist": null, "animeplanet": null, "anidb": null, "animenewsnetwork": null}, {"otakotaku": 2870, "title": "Bleach: Sennen Kessen-hen - Soukoku-tan", "myanimelist": null, "animeplanet": null, "anidb": null, "animenewsnetwork": null}, {"otakotaku": 876, "title": "Blend S", "myanimelist": null, "animeplanet": null, "anidb": null, "animenewsnetwork": null}, {"otakotaku": 2477, "title": "Blue Giant", "myanimelist": null, "animeplanet": null, "anidb": null, "animenewsnetwork": null}, {"otakotaku": 2031, "title": "Blue Lock", "myanimelist": null, "animeplanet": null, "anidb": null, "animenewsnetwork": null}, {"otakotaku": 2262, "title": "Bocchi the Rock!", "myanimelist": null, "animeplanet": null, "anidb": null, "animenewsnetwork": null}, {"otakotaku": 499, "title": "Boku no Hero Academia Season 2", "myanimelist": null, "animeplanet": null, "anidb": null, "animenewsnetwork": null}, {"otakotaku": 991, "title": "Boku no Hero Academia Season 3", "myanimelist": null, "animeplanet": null, "anidb": null, "animenewsnetwork": null}, {"otakotaku": 1423, "title": "Boku no Hero Academia Season 4", "myanimelist": null, "animeplanet": null, "anidb": null, "animenewsnetwork": null}, {"otakotaku": 1885, "title": "Boku no Hero Academia Season 5", "myanimelist": null, "animeplanet": null, "anidb": null, "animenewsnetwork": null}, {"otakotaku": 2327, "title": "Boku no Hero Academia Season 6", "myanimelist": null, "animeplanet": null, "anidb": null, "animenewsnetwork": null}, {"otakotaku": 699, "title": "Boruto: Naruto Next Generations", "myanimelist": null, "animeplanet": null, "anidb": null, "animenewsnetwork": null}, {"otakotaku": 478, "title": "Btooom!", "myanimelist": null, "animeplanet": null, "anidb": null, "animenewsnetwork": null}, {"otakotaku": 1964, "title": "Build Divide: Code Black", "myanimelist": null, "animeplanet": null, "anidb": null, "animenewsnetwork": null}, {"otakotaku": 2296, "title": "Build Divide: Code White", "myanimelist": null, "animeplanet": null, "anidb": null, "animenewsnetwork": null}, {"otakotaku": 2643, "title": "Bullbuster", "myanimelist": null, "animeplanet": null, "anidb": null, "animenewsnetwork": null}, {"otakotaku": 493, "title": "Bungou Stray Dogs Season 2", "myanimelist": null, "animeplanet": null, "anidb": null, "animenewsnetwork": null}, {"otakotaku": 1435, "title": "Bungou Stray Dogs Season 3", "myanimelist": null, "animeplanet": null, "anidb": null, "animenewsnetwork": null}, {"otakotaku": 2143, "title": "Bungou Stray Dogs Season 4", "myanimelist": null, "animeplanet": null, "anidb": null, "animenewsnetwork": null}, {"otakotaku": 2575, "title": "Bungou Stray Dogs Season 5", "myanimelist": null, "animeplanet": null, "anidb": null, "animenewsnetwork": null}, {"otakotaku": 1847, "title": "Bungou Stray Dogs Wan!", "myanimelist": null, "animeplanet": null, "anidb": null, "animenewsnetwork": null}, {"otakotaku": 863, "title": "Bungou Stray Dogs: Dead Apple", "myanimelist": null, "animeplanet": null, "anidb": null, "animenewsnetwork": null}, {"otakotaku": 1744, "title": "Burn the Witch", "myanimelist": null, "animeplanet": null, "anidb": null, "animenewsnetwork": null}, {"otakotaku": 2816, "title": "Cardfight!! Vanguard: Divinez", "myanimelist": null, "animeplanet": null, "anidb": null, "animenewsnetwork": null}, {"otakotaku": 2862, "title": "Cardfight!! Vanguard: Divinez Season 2", "myanimelist": null, "animeplanet": null, "anidb": null, "animenewsnetwork": null}, {"otakotaku": 2342, "title": "Cardfight!! Vanguard: Will+Dress", "myanimelist": null, "animeplanet": null, "anidb": null, "animenewsnetwork": null}, {"otakotaku": 2498, "title": "Cardfight!! Vanguard: Will+Dress Season 2", "myanimelist": null, "animeplanet": null, "anidb": null, "animenewsnetwork": null}, {"otakotaku": 1879, "title": "Cardfight!! Vanguard: overDress", "myanimelist": null, "animeplanet": null, "anidb": null, "animenewsnetwork": null}, {"otakotaku": 2605, "title": "Cardfight!! Vanguard: will+Dress Season 3", "myanimelist": null, "animeplanet": null, "anidb": null, "animenewsnetwork": null}, {"otakotaku": 1386, "title": "Carole & Tuesday", "myanimelist": null, "animeplanet": null, "anidb": null, "animenewsnetwork": null}, {"otakotaku": 1556, "title": "Cencoroll Connect", "myanimelist": null, "animeplanet": null, "anidb": null, "animenewsnetwork": null}, {"otakotaku": 1881, "title": "Cestvs: The Roman Fighter", "myanimelist": null, "animeplanet": null, "anidb": null, "animenewsnetwork": null}, {"otakotaku": 626, "title": "Chain Chronicle: Haecceitas no Hikari Part 1", "myanimelist": null, "animeplanet": null, "anidb": null, "animenewsnetwork": null}, {"otakotaku": 681, "title": "Chain Chronicle: Haecceitas no Hikari Part 2", "myanimelist": null, "animeplanet": null, "anidb": null, "animenewsnetwork": null}, {"otakotaku": 625, "title": "Chain Chronicle: Short Animation", "myanimelist": null, "animeplanet": null, "anidb": null, "animenewsnetwork": null}, {"otakotaku": 2291, "title": "Chimimo", "myanimelist": null, "animeplanet": null, "anidb": null, "animenewsnetwork": null}, {"otakotaku": 1427, "title": "Choukadou Girl \u2159", "myanimelist": null, "animeplanet": null, "anidb": null, "animenewsnetwork": null}, {"otakotaku": 1214, "title": "Cinderella Girls Gekijou Season 2", "myanimelist": null, "animeplanet": null, "anidb": null, "animenewsnetwork": null}, {"otakotaku": 920, "title": "Citrus", "myanimelist": null, "animeplanet": null, "anidb": null, "animenewsnetwork": null}, {"otakotaku": 2036, "title": "Cue!", "myanimelist": null, "animeplanet": null, "anidb": null, "animenewsnetwork": null}, {"otakotaku": 1916, "title": "D_Cide Traumerei the Animation", "myanimelist": null, "animeplanet": null, "anidb": null, "animenewsnetwork": null}, {"otakotaku": 369, "title": "Danganronpa: Kibou no Gakuen to Zetsubou no Koukousei The Animation", "myanimelist": null, "animeplanet": null, "anidb": null, "animenewsnetwork": null}, {"otakotaku": 873, "title": "Darling in the FranXX", "myanimelist": null, "animeplanet": null, "anidb": null, "animenewsnetwork": null}, {"otakotaku": 279, "title": "Date A Live II: Kurumi Star Festival", "myanimelist": null, "animeplanet": null, "anidb": null, "animenewsnetwork": null}, {"otakotaku": 379, "title": "Days", "myanimelist": null, "animeplanet": null, "anidb": null, "animenewsnetwork": null}, {"otakotaku": 2634, "title": "Dead Mount Death Play Part 2", "myanimelist": null, "animeplanet": null, "anidb": null, "animenewsnetwork": null}, {"otakotaku": 1774, "title": "Deca-Dence", "myanimelist": null, "animeplanet": null, "anidb": null, "animenewsnetwork": null}, {"otakotaku": 1976, "title": "Deep Insanity: The Lost Child", "myanimelist": null, "animeplanet": null, "anidb": null, "animenewsnetwork": null}, {"otakotaku": 220, "title": "Detective Conan", "myanimelist": null, "animeplanet": null, "anidb": null, "animenewsnetwork": null}, {"otakotaku": 1108, "title": "Detective Conan Movie 22: Zero's Executioner", "myanimelist": null, "animeplanet": null, "anidb": null, "animenewsnetwork": null}, {"otakotaku": 1581, "title": "Detective Conan Movie 23: The Fist of Blue Sapphire", "myanimelist": null, "animeplanet": null, "anidb": null, "animenewsnetwork": null}, {"otakotaku": 1734, "title": "Detective Conan Movie 24: Hiiro no Dangan", "myanimelist": null, "animeplanet": null, "anidb": null, "animenewsnetwork": null}, {"otakotaku": 2272, "title": "Detective Conan Movie 25: Halloween no Hanayome", "myanimelist": null, "animeplanet": null, "anidb": null, "animenewsnetwork": null}, {"otakotaku": 2807, "title": "Detective Conan Movie 26: Kurogane no Submarine", "myanimelist": null, "animeplanet": null, "anidb": null, "animenewsnetwork": null}, {"otakotaku": 1023, "title": "Devils Line", "myanimelist": null, "animeplanet": null, "anidb": null, "animenewsnetwork": null}, {"otakotaku": 891, "title": "Dia Horizon (Kabu)", "myanimelist": null, "animeplanet": null, "anidb": null, "animenewsnetwork": null}, {"otakotaku": 420, "title": "Diabolik Lovers", "myanimelist": null, "animeplanet": null, "anidb": null, "animenewsnetwork": null}, {"otakotaku": 422, "title": "Diabolik Lovers More,Blood", "myanimelist": null, "animeplanet": null, "anidb": null, "animenewsnetwork": null}, {"otakotaku": 421, "title": "Diabolik Lovers OVA", "myanimelist": null, "animeplanet": null, "anidb": null, "animenewsnetwork": null}, {"otakotaku": 859, "title": "Dies Irae", "myanimelist": null, "animeplanet": null, "anidb": null, "animenewsnetwork": null}, {"otakotaku": 1034, "title": "Dies Irae: To the Ring Reincarnation", "myanimelist": null, "animeplanet": null, "anidb": null, "animenewsnetwork": null}, {"otakotaku": 2212, "title": "Dog Days''", "myanimelist": null, "animeplanet": null, "anidb": null, "animenewsnetwork": null}, {"otakotaku": 2646, "title": "Dog Signal", "myanimelist": null, "animeplanet": null, "anidb": null, "animenewsnetwork": null}, {"otakotaku": 1679, "title": "Dokyuu H* HxEros", "myanimelist": null, "animeplanet": null, "anidb": null, "animenewsnetwork": null}, {"otakotaku": 1381, "title": "Dr. Stone", "myanimelist": null, "animeplanet": null, "anidb": null, "animenewsnetwork": null}, {"otakotaku": 2386, "title": "Dr. Stone: New World", "myanimelist": null, "animeplanet": null, "anidb": null, "animenewsnetwork": null}, {"otakotaku": 2631, "title": "Dr. Stone: New World Part 2", "myanimelist": null, "animeplanet": null, "anidb": null, "animenewsnetwork": null}, {"otakotaku": 2328, "title": "Dr. Stone: Ryuusui", "myanimelist": null, "animeplanet": null, "anidb": null, "animenewsnetwork": null}, {"otakotaku": 1700, "title": "Dr. Stone: Stone Wars", "myanimelist": null, "animeplanet": null, "anidb": null, "animenewsnetwork": null}, {"otakotaku": 2835, "title": "Dragon Ball Daima", "myanimelist": null, "animeplanet": null, "anidb": null, "animenewsnetwork": null}, {"otakotaku": 2271, "title": "Dragon Ball Super: Super Hero", "myanimelist": null, "animeplanet": null, "anidb": null, "animenewsnetwork": null}, {"otakotaku": 383, "title": "Dungeon ni Deai wo Motomeru no wa Machigatteiru Darou ka", "myanimelist": null, "animeplanet": null, "anidb": null, "animenewsnetwork": null}, {"otakotaku": 717, "title": "Dungeon ni Deai wo Motomeru no wa Machigatteiru Darou ka Gaiden: Sword Oratoria", "myanimelist": null, "animeplanet": null, "anidb": null, "animenewsnetwork": null}, {"otakotaku": 1069, "title": "Dungeon ni Deai wo Motomeru no wa Machigatteiru Darou ka II", "myanimelist": null, "animeplanet": null, "anidb": null, "animenewsnetwork": null}, {"otakotaku": 1746, "title": "Dungeon ni Deai wo Motomeru no wa Machigatteiru Darou ka III", "myanimelist": null, "animeplanet": null, "anidb": null, "animenewsnetwork": null}, {"otakotaku": 1816, "title": "Edens Zero", "myanimelist": null, "animeplanet": null, "anidb": null, "animenewsnetwork": null}, {"otakotaku": 2436, "title": "Edens Zero Season 2", "myanimelist": null, "animeplanet": null, "anidb": null, "animenewsnetwork": null}, {"otakotaku": 2368, "title": "Eiga Daisuki Pompo-san (Movie)", "myanimelist": null, "animeplanet": null, "anidb": null, "animenewsnetwork": null}, {"otakotaku": 1428, "title": "Enen no Shouboutai", "myanimelist": null, "animeplanet": null, "anidb": null, "animenewsnetwork": null}, {"otakotaku": 2266, "title": "Estab-Life: Great Escape", "myanimelist": null, "animeplanet": null, "anidb": null, "animenewsnetwork": null}, {"otakotaku": 2332, "title": "Eternal Boys", "myanimelist": null, "animeplanet": null, "anidb": null, "animenewsnetwork": null}, {"otakotaku": 2033, "title": "Evangelion: 3.0+1.0 Thrice Upon a Time", "myanimelist": null, "animeplanet": null, "anidb": null, "animenewsnetwork": null}, {"otakotaku": 942, "title": "Evil or Live", "myanimelist": null, "animeplanet": null, "anidb": null, "animenewsnetwork": null}, {"otakotaku": 1759, "title": "Ex-Arm", "myanimelist": null, "animeplanet": null, "anidb": null, "animenewsnetwork": null}, {"otakotaku": 2757, "title": "Fairy Tail: 100 Years Quest", "myanimelist": null, "animeplanet": null, "anidb": null, "animenewsnetwork": null}, {"otakotaku": 360, "title": "Fate/Extra Last Encore", "myanimelist": null, "animeplanet": null, "anidb": null, "animenewsnetwork": null}, {"otakotaku": 1195, "title": "Fate/Extra: Last Encore - Irusterias Tendouron", "myanimelist": null, "animeplanet": null, "anidb": null, "animenewsnetwork": null}, {"otakotaku": 1035, "title": "Fate/Grand Order: Moonlight/Lostroom", "myanimelist": null, "animeplanet": null, "anidb": null, "animenewsnetwork": null}, {"otakotaku": 1252, "title": "Fate/Grand Order: Shinsei Entaku Ryouiki Camelot 1 - Wandering; Agateram", "myanimelist": null, "animeplanet": null, "anidb": null, "animenewsnetwork": null}, {"otakotaku": 165, "title": "Fate/stay night Movie: Heaven's Feel - I. Presage Flower", "myanimelist": null, "animeplanet": null, "anidb": null, "animenewsnetwork": null}, {"otakotaku": 952, "title": "Fate/stay night Movie: Heaven's Feel - II. Lost Butterfly", "myanimelist": null, "animeplanet": null, "anidb": null, "animenewsnetwork": null}, {"otakotaku": 1157, "title": "Fate/stay night Movie: Heaven's Feel - III. Spring Song", "myanimelist": null, "animeplanet": null, "anidb": null, "animenewsnetwork": null}, {"otakotaku": 149, "title": "Fate/stay night: Unlimited Blade Works 2nd Season - Sunny Day", "myanimelist": null, "animeplanet": null, "anidb": null, "animenewsnetwork": null}, {"otakotaku": 2485, "title": "Flaglia", "myanimelist": null, "animeplanet": null, "anidb": null, "animenewsnetwork": null}, {"otakotaku": 807, "title": "Free! Movie 1: Timeless Medley - Kizuna", "myanimelist": null, "animeplanet": null, "anidb": null, "animenewsnetwork": null}, {"otakotaku": 843, "title": "Free! Movie 2: Timeless Medley - Yakusoku", "myanimelist": null, "animeplanet": null, "anidb": null, "animenewsnetwork": null}, {"otakotaku": 1582, "title": "Free! Movie 3: Road to the World - Yume", "myanimelist": null, "animeplanet": null, "anidb": null, "animenewsnetwork": null}, {"otakotaku": 2005, "title": "Free! Movie 4: The Final Stroke", "myanimelist": null, "animeplanet": null, "anidb": null, "animenewsnetwork": null}, {"otakotaku": 2217, "title": "Free! Movie 5: The Final Stroke", "myanimelist": null, "animeplanet": null, "anidb": null, "animenewsnetwork": null}, {"otakotaku": 2141, "title": "Fruits Basket: Prelude", "myanimelist": null, "animeplanet": null, "anidb": null, "animenewsnetwork": null}, {"otakotaku": 1724, "title": "Fugou Keiji: Balance:Unlimited", "myanimelist": null, "animeplanet": null, "anidb": null, "animenewsnetwork": null}, {"otakotaku": 512, "title": "Fw:Hamatora", "myanimelist": null, "animeplanet": null, "anidb": null, "animenewsnetwork": null}, {"otakotaku": 629, "title": "Gamers!", "myanimelist": null, "animeplanet": null, "anidb": null, "animenewsnetwork": null}, {"otakotaku": 2034, "title": "Ganbare Douki-chan (ONA)", "myanimelist": null, "animeplanet": null, "anidb": null, "animenewsnetwork": null}, {"otakotaku": 611, "title": "Gantz:O", "myanimelist": null, "animeplanet": null, "anidb": null, "animenewsnetwork": null}, {"otakotaku": 923, "title": "Garo: Vanishing Line", "myanimelist": null, "animeplanet": null, "anidb": null, "animenewsnetwork": null}, {"otakotaku": 2210, "title": "Garugaku. II: Lucky Stars", "myanimelist": null, "animeplanet": null, "anidb": null, "animenewsnetwork": null}, {"otakotaku": 2209, "title": "Garugaku.: Sei Girls Square Gakuin", "myanimelist": null, "animeplanet": null, "anidb": null, "animenewsnetwork": null}, {"otakotaku": 1833, "title": "Gekidol: Actidol Project", "myanimelist": null, "animeplanet": null, "anidb": null, "animenewsnetwork": null}, {"otakotaku": 2539, "title": "Genjitsu no Yohane: Sunshine in the Mirror", "myanimelist": null, "animeplanet": null, "anidb": null, "animenewsnetwork": null}, {"otakotaku": 1370, "title": "Ghost in the Shell", "myanimelist": null, "animeplanet": null, "anidb": null, "animenewsnetwork": null}, {"otakotaku": 1745, "title": "Ghost in the Shell: SAC_2045", "myanimelist": null, "animeplanet": null, "anidb": null, "animenewsnetwork": null}, {"otakotaku": 1660, "title": "Gibiate", "myanimelist": null, "animeplanet": null, "anidb": null, "animenewsnetwork": null}, {"otakotaku": 1029, "title": "Gintama.: Shirogane no Tamashii-hen", "myanimelist": null, "animeplanet": null, "anidb": null, "animenewsnetwork": null}, {"otakotaku": 1129, "title": "Gintama.: Shirogane no Tamashii-hen - Kouhan-sen", "myanimelist": null, "animeplanet": null, "anidb": null, "animenewsnetwork": null}, {"otakotaku": 381, "title": "Girls & Panzer", "myanimelist": null, "animeplanet": null, "anidb": null, "animenewsnetwork": null}, {"otakotaku": 382, "title": "Girls & Panzer Movie", "myanimelist": null, "animeplanet": null, "anidb": null, "animenewsnetwork": null}, {"otakotaku": 1508, "title": "Girls & Panzer: Saishuushou Part 1", "myanimelist": null, "animeplanet": null, "anidb": null, "animenewsnetwork": null}, {"otakotaku": 1515, "title": "Girls & Panzer: Saishuushou Part 2", "myanimelist": null, "animeplanet": null, "anidb": null, "animenewsnetwork": null}, {"otakotaku": 2263, "title": "Girls & Panzer: Saishuushou Part 3", "myanimelist": null, "animeplanet": null, "anidb": null, "animenewsnetwork": null}, {"otakotaku": 2739, "title": "Girls Band Cry", "myanimelist": null, "animeplanet": null, "anidb": null, "animenewsnetwork": null}, {"otakotaku": 2519, "title": "Goblin Slayer II", "myanimelist": null, "animeplanet": null, "anidb": null, "animenewsnetwork": null}, {"otakotaku": 1644, "title": "Goblin Slayer: Goblin's Crown", "myanimelist": null, "animeplanet": null, "anidb": null, "animenewsnetwork": null}, {"otakotaku": 1291, "title": "Golden Kamuy Season 2", "myanimelist": null, "animeplanet": null, "anidb": null, "animenewsnetwork": null}, {"otakotaku": 1461, "title": "Golden Kamuy Season 2 OVA", "myanimelist": null, "animeplanet": null, "anidb": null, "animenewsnetwork": null}, {"otakotaku": 1261, "title": "Gotoubun no Hanayome", "myanimelist": null, "animeplanet": null, "anidb": null, "animenewsnetwork": null}, {"otakotaku": 1570, "title": "Gotoubun no Hanayome \u222c", "myanimelist": null, "animeplanet": null, "anidb": null, "animenewsnetwork": null}, {"otakotaku": 1513, "title": "Granbelm", "myanimelist": null, "animeplanet": null, "anidb": null, "animenewsnetwork": null}, {"otakotaku": 637, "title": "Granblue Fantasy The Animation", "myanimelist": null, "animeplanet": null, "anidb": null, "animenewsnetwork": null}, {"otakotaku": 1526, "title": "Granblue Fantasy The Animation Season 2", "myanimelist": null, "animeplanet": null, "anidb": null, "animenewsnetwork": null}, {"otakotaku": 1702, "title": "Granblue Fantasy The Animation Season 2 Extras", "myanimelist": null, "animeplanet": null, "anidb": null, "animenewsnetwork": null}, {"otakotaku": 1721, "title": "Great Pretender", "myanimelist": null, "animeplanet": null, "anidb": null, "animenewsnetwork": null}, {"otakotaku": 1623, "title": "Gundam Build Divers Re:Rise", "myanimelist": null, "animeplanet": null, "anidb": null, "animenewsnetwork": null}, {"otakotaku": 1294, "title": "Gurazeni: Season 2", "myanimelist": null, "animeplanet": null, "anidb": null, "animenewsnetwork": null}, {"otakotaku": 472, "title": "H* Ouji to Warawanai Neko.", "myanimelist": null, "animeplanet": null, "anidb": null, "animenewsnetwork": null}, {"otakotaku": 324, "title": "Hai to Gensou no Grimgar: Furoagari no Kabe ni Kaketa Seishun - One More Centimeter", "myanimelist": null, "animeplanet": null, "anidb": null, "animenewsnetwork": null}, {"otakotaku": 134, "title": "Haikyuu!!", "myanimelist": null, "animeplanet": null, "anidb": null, "animenewsnetwork": null}, {"otakotaku": 2738, "title": "Haikyuu!! Movie: Gomisuteba no Kessen", "myanimelist": null, "animeplanet": null, "anidb": null, "animenewsnetwork": null}, {"otakotaku": 135, "title": "Haikyuu!! Second Season", "myanimelist": null, "animeplanet": null, "anidb": null, "animenewsnetwork": null}, {"otakotaku": 494, "title": "Haikyuu!!: Karasuno Koukou VS Shiratorizawa Gakuen Koukou", "myanimelist": null, "animeplanet": null, "anidb": null, "animenewsnetwork": null}, {"otakotaku": 1649, "title": "Haikyuu!!: Riku vs. Kuu", "myanimelist": null, "animeplanet": null, "anidb": null, "animenewsnetwork": null}, {"otakotaku": 1630, "title": "Haikyuu!!: To the Top", "myanimelist": null, "animeplanet": null, "anidb": null, "animenewsnetwork": null}, {"otakotaku": 1767, "title": "Haikyuu!!: To the Top Season 2", "myanimelist": null, "animeplanet": null, "anidb": null, "animenewsnetwork": null}, {"otakotaku": 930, "title": "Hajimete no Gal: Hajimete no Bunkasai", "myanimelist": null, "animeplanet": null, "anidb": null, "animenewsnetwork": null}, {"otakotaku": 1114, "title": "Hanayamata", "myanimelist": null, "animeplanet": null, "anidb": null, "animenewsnetwork": null}, {"otakotaku": 1059, "title": "Hanebado!", "myanimelist": null, "animeplanet": null, "anidb": null, "animenewsnetwork": null}, {"otakotaku": 2048, "title": "Hanma Baki: Son of Ogre", "myanimelist": null, "animeplanet": null, "anidb": null, "animenewsnetwork": null}, {"otakotaku": 2599, "title": "Hanma Baki: Son of Ogre Season 2", "myanimelist": null, "animeplanet": null, "anidb": null, "animenewsnetwork": null}, {"otakotaku": 1771, "title": "Hanyou no Yashahime: Sengoku Otogizoushi", "myanimelist": null, "animeplanet": null, "anidb": null, "animenewsnetwork": null}, {"otakotaku": 1997, "title": "Hanyou no Yashahime: Sengoku Otogizoushi - Ni no Shou", "myanimelist": null, "animeplanet": null, "anidb": null, "animenewsnetwork": null}, {"otakotaku": 1795, "title": "Hataraku Saibou!!: Saikyou no Teki, Futatabi. Karada no Naka wa \"Chou\" Oosawagi!", "myanimelist": null, "animeplanet": null, "anidb": null, "animenewsnetwork": null}, {"otakotaku": 725, "title": "Hatsukoi Monster: Mou Chotto dake Tsuzukunja", "myanimelist": null, "animeplanet": null, "anidb": null, "animenewsnetwork": null}, {"otakotaku": 2583, "title": "Hibike! Euphonium: Ensemble Contest-hen", "myanimelist": null, "animeplanet": null, "anidb": null, "animenewsnetwork": null}, {"otakotaku": 2408, "title": "High Card", "myanimelist": null, "animeplanet": null, "anidb": null, "animenewsnetwork": null}, {"otakotaku": 2690, "title": "High Card Season 2", "myanimelist": null, "animeplanet": null, "anidb": null, "animenewsnetwork": null}, {"otakotaku": 2736, "title": "Highspeed Etoile", "myanimelist": null, "animeplanet": null, "anidb": null, "animenewsnetwork": null}, {"otakotaku": 1036, "title": "Hinomaruzumou", "myanimelist": null, "animeplanet": null, "anidb": null, "animenewsnetwork": null}, {"otakotaku": 1284, "title": "Hitoribocchi no Marumaru Seikatsu", "myanimelist": null, "animeplanet": null, "anidb": null, "animenewsnetwork": null}, {"otakotaku": 1696, "title": "Honzuki no Gekokujou: Shisho ni Naru Tame ni wa Shudan wo Erandeiraremasen Season 2", "myanimelist": null, "animeplanet": null, "anidb": null, "animenewsnetwork": null}, {"otakotaku": 1080, "title": "Hoozuki no Reitetsu 2nd Season: Sono Ni", "myanimelist": null, "animeplanet": null, "anidb": null, "animenewsnetwork": null}, {"otakotaku": 2573, "title": "Horimiya: Piece", "myanimelist": null, "animeplanet": null, "anidb": null, "animenewsnetwork": null}, {"otakotaku": 879, "title": "Houseki no Kuni (ONA)", "myanimelist": null, "animeplanet": null, "anidb": null, "animenewsnetwork": null}, {"otakotaku": 2432, "title": "Human Bug Daigaku: Fushi Gakubu Fukou Gakka", "myanimelist": null, "animeplanet": null, "anidb": null, "animenewsnetwork": null}, {"otakotaku": 1546, "title": "Human Lost: Ningen Shikkaku", "myanimelist": null, "animeplanet": null, "anidb": null, "animenewsnetwork": null}, {"otakotaku": 1768, "title": "Hypnosis Mic: Division Rap Battle - Rhyme Anima", "myanimelist": null, "animeplanet": null, "anidb": null, "animenewsnetwork": null}, {"otakotaku": 2629, "title": "Hypnosis Mic: Division Rap Battle - Rhyme Anima +", "myanimelist": null, "animeplanet": null, "anidb": null, "animenewsnetwork": null}, {"otakotaku": 1627, "title": "ID:Invaded", "myanimelist": null, "animeplanet": null, "anidb": null, "animenewsnetwork": null}, {"otakotaku": 1676, "title": "IDOLiSH7: Second Beat!", "myanimelist": null, "animeplanet": null, "anidb": null, "animenewsnetwork": null}, {"otakotaku": 1945, "title": "IDOLiSH7: Third Beat!", "myanimelist": null, "animeplanet": null, "anidb": null, "animenewsnetwork": null}, {"otakotaku": 2402, "title": "IDOLiSH7: Third Beat! Part 2", "myanimelist": null, "animeplanet": null, "anidb": null, "animenewsnetwork": null}, {"otakotaku": 679, "title": "IT Gijinka Keikaku", "myanimelist": null, "animeplanet": null, "anidb": null, "animenewsnetwork": null}, {"otakotaku": 1412, "title": "Ikebukuro PR Anime", "myanimelist": null, "animeplanet": null, "anidb": null, "animenewsnetwork": null}, {"otakotaku": 1409, "title": "Ikkitousen", "myanimelist": null, "animeplanet": null, "anidb": null, "animenewsnetwork": null}, {"otakotaku": 2355, "title": "Inu-Ou", "myanimelist": null, "animeplanet": null, "anidb": null, "animenewsnetwork": null}, {"otakotaku": 2419, "title": "Isekai One Turn Kill Neesan: Ane Douhan no Isekai Seikatsu Hajimemashita", "myanimelist": null, "animeplanet": null, "anidb": null, "animenewsnetwork": null}, {"otakotaku": 1324, "title": "Isekai Quartet", "myanimelist": null, "animeplanet": null, "anidb": null, "animenewsnetwork": null}, {"otakotaku": 1982, "title": "Isekai Quartet: Another World", "myanimelist": null, "animeplanet": null, "anidb": null, "animenewsnetwork": null}, {"otakotaku": 2764, "title": "Isekai Suicide Squad", "myanimelist": null, "animeplanet": null, "anidb": null, "animenewsnetwork": null}, {"otakotaku": 1004, "title": "Island", "myanimelist": null, "animeplanet": null, "anidb": null, "animenewsnetwork": null}, {"otakotaku": 1160, "title": "Iya na Kao sare nagara Opantsu Misete Moraitai", "myanimelist": null, "animeplanet": null, "anidb": null, "animenewsnetwork": null}, {"otakotaku": 1845, "title": "I\u2605Chu: Halfway Through the Idol", "myanimelist": null, "animeplanet": null, "anidb": null, "animenewsnetwork": null}, {"otakotaku": 2538, "title": "Jaku-Chara Tomozaki-kun 2nd Stage", "myanimelist": null, "animeplanet": null, "anidb": null, "animenewsnetwork": null}, {"otakotaku": 2169, "title": "JoJo no Kimyou na Bouken Part 3: Stardust Crusaders Season 2", "myanimelist": null, "animeplanet": null, "anidb": null, "animenewsnetwork": null}, {"otakotaku": 2026, "title": "JoJo no Kimyou na Bouken Part 6: Stone Ocean", "myanimelist": null, "animeplanet": null, "anidb": null, "animenewsnetwork": null}, {"otakotaku": 285, "title": "Joker Game", "myanimelist": null, "animeplanet": null, "anidb": null, "animenewsnetwork": null}, {"otakotaku": 520, "title": "Joker Game: Kuroneko Yoru no Bouken", "myanimelist": null, "animeplanet": null, "anidb": null, "animenewsnetwork": null}, {"otakotaku": 1468, "title": "Joshikausei", "myanimelist": null, "animeplanet": null, "anidb": null, "animenewsnetwork": null}, {"otakotaku": 1204, "title": "Joshiochi!: 2-kai kara Onnanoko ga... Futtekita!?", "myanimelist": null, "animeplanet": null, "anidb": null, "animenewsnetwork": null}, {"otakotaku": 1886, "title": "Jouran: The Princess of Snow and Blood", "myanimelist": null, "animeplanet": null, "anidb": null, "animenewsnetwork": null}, {"otakotaku": 2077, "title": "Journey: Taiko Arabia Hantou de no Kiseki to Tatakai no Monogatari", "myanimelist": null, "animeplanet": null, "anidb": null, "animenewsnetwork": null}, {"otakotaku": 1970, "title": "Jujutsu Kaisen 0 Movie", "myanimelist": null, "animeplanet": null, "anidb": null, "animenewsnetwork": null}, {"otakotaku": 2440, "title": "Jujutsu Kaisen Season 2", "myanimelist": null, "animeplanet": null, "anidb": null, "animenewsnetwork": null}, {"otakotaku": 320, "title": "K-On!", "myanimelist": null, "animeplanet": null, "anidb": null, "animenewsnetwork": null}, {"otakotaku": 321, "title": "K-On!!", "myanimelist": null, "animeplanet": null, "anidb": null, "animenewsnetwork": null}, {"otakotaku": 1130, "title": "K: Seven Stories Movie 1 - R:B - Blaze", "myanimelist": null, "animeplanet": null, "anidb": null, "animenewsnetwork": null}, {"otakotaku": 1161, "title": "K: Seven Stories Movie 2 - Side:Blue - Tenrou no Gotoku", "myanimelist": null, "animeplanet": null, "anidb": null, "animenewsnetwork": null}, {"otakotaku": 1162, "title": "K: Seven Stories Movie 3 - Side:Green - Uwagaki Sekai", "myanimelist": null, "animeplanet": null, "anidb": null, "animenewsnetwork": null}, {"otakotaku": 1309, "title": "K: Seven Stories Movie 5 - Memory of Red - Burn", "myanimelist": null, "animeplanet": null, "anidb": null, "animenewsnetwork": null}, {"otakotaku": 1310, "title": "K: Seven Stories Movie 6 - Circle Vision - Nameless Song", "myanimelist": null, "animeplanet": null, "anidb": null, "animenewsnetwork": null}, {"otakotaku": 2012, "title": "Kaginado", "myanimelist": null, "animeplanet": null, "anidb": null, "animenewsnetwork": null}, {"otakotaku": 2256, "title": "Kaginado Season 2", "myanimelist": null, "animeplanet": null, "anidb": null, "animenewsnetwork": null}, {"otakotaku": 2279, "title": "Kaitou Queen wa Circus ga Osuki", "myanimelist": null, "animeplanet": null, "anidb": null, "animenewsnetwork": null}, {"otakotaku": 2147, "title": "Kakegurui Twin", "myanimelist": null, "animeplanet": null, "anidb": null, "animenewsnetwork": null}, {"otakotaku": 2413, "title": "Kami no Tou: Ouji no Kikan", "myanimelist": null, "animeplanet": null, "anidb": null, "animenewsnetwork": null}, {"otakotaku": 2637, "title": "Kamierabi", "myanimelist": null, "animeplanet": null, "anidb": null, "animenewsnetwork": null}, {"otakotaku": 2259, "title": "Kanojo, Okarishimasu Season 2", "myanimelist": null, "animeplanet": null, "anidb": null, "animenewsnetwork": null}, {"otakotaku": 849, "title": "Karadasagashi", "myanimelist": null, "animeplanet": null, "anidb": null, "animenewsnetwork": null}, {"otakotaku": 1209, "title": "Karakai Jouzu no Takagi-san: Water Slide", "myanimelist": null, "animeplanet": null, "anidb": null, "animenewsnetwork": null}, {"otakotaku": 718, "title": "Katsugeki/Touken Ranbu", "myanimelist": null, "animeplanet": null, "anidb": null, "animenewsnetwork": null}, {"otakotaku": 2238, "title": "Katsugeki/Touken Ranbu Movie", "myanimelist": null, "animeplanet": null, "anidb": null, "animenewsnetwork": null}, {"otakotaku": 1202, "title": "Kekkai Sensen & Beyond: Zapp Renfro Ingaouhouchuu!!/Baccardio no Shizuku", "myanimelist": null, "animeplanet": null, "anidb": null, "animenewsnetwork": null}, {"otakotaku": 2600, "title": "Kengan Ashura Season 2", "myanimelist": null, "animeplanet": null, "anidb": null, "animenewsnetwork": null}, {"otakotaku": 2839, "title": "Kengan Ashura Season 2 Part 2", "myanimelist": null, "animeplanet": null, "anidb": null, "animenewsnetwork": null}, {"otakotaku": 2733, "title": "Kenka Dokugaku", "myanimelist": null, "animeplanet": null, "anidb": null, "animenewsnetwork": null}, {"otakotaku": 969, "title": "Killing Bites", "myanimelist": null, "animeplanet": null, "anidb": null, "animenewsnetwork": null}, {"otakotaku": 2112, "title": "Kindaichi Shounen no Jikenbo Returns Season 2", "myanimelist": null, "animeplanet": null, "anidb": null, "animenewsnetwork": null}, {"otakotaku": 1801, "title": "King's Raid: Ishi wo Tsugumono-tachi", "myanimelist": null, "animeplanet": null, "anidb": null, "animenewsnetwork": null}, {"otakotaku": 2260, "title": "Kingdom Season 4", "myanimelist": null, "animeplanet": null, "anidb": null, "animenewsnetwork": null}, {"otakotaku": 2755, "title": "Kinnikuman: Kanpeki Ch\u043eujin Shiso-hen", "myanimelist": null, "animeplanet": null, "anidb": null, "animenewsnetwork": null}, {"otakotaku": 1376, "title": "Kiss x Sis (OVA)", "myanimelist": null, "animeplanet": null, "anidb": null, "animenewsnetwork": null}, {"otakotaku": 281, "title": "Kiznaiver", "myanimelist": null, "animeplanet": null, "anidb": null, "animenewsnetwork": null}, {"otakotaku": 133, "title": "Kizumonogatari I: Tekketsu-hen", "myanimelist": null, "animeplanet": null, "anidb": null, "animenewsnetwork": null}, {"otakotaku": 152, "title": "Kizumonogatari II: Nekketsu-hen", "myanimelist": null, "animeplanet": null, "anidb": null, "animenewsnetwork": null}, {"otakotaku": 153, "title": "Kizumonogatari III: Reiketsu-hen", "myanimelist": null, "animeplanet": null, "anidb": null, "animenewsnetwork": null}, {"otakotaku": 846, "title": "Koukyoushihen Eureka Seven", "myanimelist": null, "animeplanet": null, "anidb": null, "animenewsnetwork": null}, {"otakotaku": 1240, "title": "Koukyoushihen Eureka Seven Hi-Evolution 2: Anemone", "myanimelist": null, "animeplanet": null, "anidb": null, "animenewsnetwork": null}, {"otakotaku": 1311, "title": "Koukyoushihen Eureka Seven Hi-Evolution 3: Eureka", "myanimelist": null, "animeplanet": null, "anidb": null, "animenewsnetwork": null}, {"otakotaku": 592, "title": "Koutetsujou no Kabaneri Movie 1: Tsudou Hikari", "myanimelist": null, "animeplanet": null, "anidb": null, "animenewsnetwork": null}, {"otakotaku": 684, "title": "Koutetsujou no Kabaneri Movie 2: Moeru Inochi", "myanimelist": null, "animeplanet": null, "anidb": null, "animenewsnetwork": null}, {"otakotaku": 270, "title": "Kuma Miko", "myanimelist": null, "animeplanet": null, "anidb": null, "animenewsnetwork": null}, {"otakotaku": 376, "title": "Kuma Miko Specials", "myanimelist": null, "animeplanet": null, "anidb": null, "animenewsnetwork": null}, {"otakotaku": 2763, "title": "Kuramerukagari", "myanimelist": null, "animeplanet": null, "anidb": null, "animenewsnetwork": null}, {"otakotaku": 509, "title": "Kuroko no Basket Movie 1: Winter Cup Soushuuhen - Kage to Hikari", "myanimelist": null, "animeplanet": null, "anidb": null, "animenewsnetwork": null}, {"otakotaku": 582, "title": "Kuroko no Basket Movie 2: Winter Cup Soushuuhen - Namida no Saki e", "myanimelist": null, "animeplanet": null, "anidb": null, "animenewsnetwork": null}, {"otakotaku": 583, "title": "Kuroko no Basket Movie 3: Winter Cup Soushuuhen - Tobira no Mukou", "myanimelist": null, "animeplanet": null, "anidb": null, "animenewsnetwork": null}, {"otakotaku": 1431, "title": "Kyochuu Rettou (OVA)", "myanimelist": null, "animeplanet": null, "anidb": null, "animenewsnetwork": null}, {"otakotaku": 301, "title": "Kyoukai no Rinne Season 2", "myanimelist": null, "animeplanet": null, "anidb": null, "animenewsnetwork": null}, {"otakotaku": 1088, "title": "Ladyspo", "myanimelist": null, "animeplanet": null, "anidb": null, "animenewsnetwork": null}, {"otakotaku": 1722, "title": "Listeners", "myanimelist": null, "animeplanet": null, "anidb": null, "animenewsnetwork": null}, {"otakotaku": 604, "title": "Little Witch Academia (Movie)", "myanimelist": null, "animeplanet": null, "anidb": null, "animenewsnetwork": null}, {"otakotaku": 2324, "title": "Love Live! Superstar!! Season 2", "myanimelist": null, "animeplanet": null, "anidb": null, "animenewsnetwork": null}, {"otakotaku": 2610, "title": "MF Ghost", "myanimelist": null, "animeplanet": null, "anidb": null, "animenewsnetwork": null}, {"otakotaku": 2897, "title": "MF Ghost 2nd Season", "myanimelist": null, "animeplanet": null, "anidb": null, "animenewsnetwork": null}, {"otakotaku": 2062, "title": "Macross \u0394 Movie 2: Zettai Live!!!", "myanimelist": null, "animeplanet": null, "anidb": null, "animenewsnetwork": null}, {"otakotaku": 839, "title": "Made in Abyss", "myanimelist": null, "animeplanet": null, "anidb": null, "animenewsnetwork": null}, {"otakotaku": 1247, "title": "Made in Abyss Movie 1: Tabidachi no Yoake", "myanimelist": null, "animeplanet": null, "anidb": null, "animenewsnetwork": null}, {"otakotaku": 1248, "title": "Made in Abyss Movie 2: Hourou suru Tasogare", "myanimelist": null, "animeplanet": null, "anidb": null, "animenewsnetwork": null}, {"otakotaku": 1547, "title": "Made in Abyss Movie 3: Fukaki Tamashii no Reimei", "myanimelist": null, "animeplanet": null, "anidb": null, "animenewsnetwork": null}, {"otakotaku": 2056, "title": "Made in Abyss: Retsujitsu no Ougonkyou", "myanimelist": null, "animeplanet": null, "anidb": null, "animenewsnetwork": null}, {"otakotaku": 2785, "title": "Madougushi Dahliya wa Utsumukanai", "myanimelist": null, "animeplanet": null, "anidb": null, "animenewsnetwork": null}, {"otakotaku": 1810, "title": "Magatsu Wahrheit: Zuerst", "myanimelist": null, "animeplanet": null, "anidb": null, "animenewsnetwork": null}, {"otakotaku": 253, "title": "Magi: Sinbad no Bouken (OVA)", "myanimelist": null, "animeplanet": null, "anidb": null, "animenewsnetwork": null}, {"otakotaku": 1298, "title": "Mahou Shoujo Lyrical Nanoha: Detonation", "myanimelist": null, "animeplanet": null, "anidb": null, "animenewsnetwork": null}, {"otakotaku": 2474, "title": "Mahoutsukai no Yome Season 2", "myanimelist": null, "animeplanet": null, "anidb": null, "animenewsnetwork": null}, {"otakotaku": 2624, "title": "Mahoutsukai no Yome Season 2 Part 2", "myanimelist": null, "animeplanet": null, "anidb": null, "animenewsnetwork": null}, {"otakotaku": 1860, "title": "Mairimashita! Iruma-kun Season 2", "myanimelist": null, "animeplanet": null, "anidb": null, "animenewsnetwork": null}, {"otakotaku": 2740, "title": "Maou Gakuin no Futekigousha II: Shijou Saikyou no Maou no Shiso, Tensei shite Shison-tachi no Gakkou e Kayou Part 2", "myanimelist": null, "animeplanet": null, "anidb": null, "animenewsnetwork": null}, {"otakotaku": 1710, "title": "Maou Gakuin no Futekigousha: Shijou Saikyou no Maou no Shiso, Tensei shite Shison-tachi no Gakkou e Kayou", "myanimelist": null, "animeplanet": null, "anidb": null, "animenewsnetwork": null}, {"otakotaku": 2218, "title": "Maou Gakuin no Futekigousha: Shijou Saikyou no Maou no Shiso, Tensei shite Shison-tachi no Gakkou e Kayou II", "myanimelist": null, "animeplanet": null, "anidb": null, "animenewsnetwork": null}, {"otakotaku": 1852, "title": "Mars Red", "myanimelist": null, "animeplanet": null, "anidb": null, "animenewsnetwork": null}, {"otakotaku": 2380, "title": "Mashle", "myanimelist": null, "animeplanet": null, "anidb": null, "animenewsnetwork": null}, {"otakotaku": 2682, "title": "Mashle: Shinkakusha Kouho Senbatsu Shiken-hen", "myanimelist": null, "animeplanet": null, "anidb": null, "animenewsnetwork": null}, {"otakotaku": 2750, "title": "Mayonaka Punch", "myanimelist": null, "animeplanet": null, "anidb": null, "animenewsnetwork": null}, {"otakotaku": 927, "title": "Mazinger Z Movie: Infinity", "myanimelist": null, "animeplanet": null, "anidb": null, "animenewsnetwork": null}, {"otakotaku": 2590, "title": "Mecha-ude", "myanimelist": null, "animeplanet": null, "anidb": null, "animenewsnetwork": null}, {"otakotaku": 1173, "title": "Mecha-ude (ONA)", "myanimelist": null, "animeplanet": null, "anidb": null, "animenewsnetwork": null}, {"otakotaku": 2144, "title": "Meitantei Conan: Keisatsu Gakkou-hen - Wild Police Story", "myanimelist": null, "animeplanet": null, "anidb": null, "animenewsnetwork": null}, {"otakotaku": 2284, "title": "Meitantei Conan: Zero no Tea Time", "myanimelist": null, "animeplanet": null, "anidb": null, "animenewsnetwork": null}, {"otakotaku": 215, "title": "Mekakucity Actors", "myanimelist": null, "animeplanet": null, "anidb": null, "animenewsnetwork": null}, {"otakotaku": 118, "title": "Mirai Nikki", "myanimelist": null, "animeplanet": null, "anidb": null, "animenewsnetwork": null}, {"otakotaku": 1438, "title": "Mix: Meisei Story", "myanimelist": null, "animeplanet": null, "anidb": null, "animenewsnetwork": null}, {"otakotaku": 2512, "title": "Mix: Meisei Story - Nidome no Natsu, Sora no Mukou e", "myanimelist": null, "animeplanet": null, "anidb": null, "animenewsnetwork": null}, {"otakotaku": 1592, "title": "Mo Dao Zu Shi: Xian Yun Pian", "myanimelist": null, "animeplanet": null, "anidb": null, "animenewsnetwork": null}, {"otakotaku": 298, "title": "Mobile Suit Gundam Unicorn", "myanimelist": null, "animeplanet": null, "anidb": null, "animenewsnetwork": null}, {"otakotaku": 299, "title": "Mobile Suit Gundam Unicorn RE:0096", "myanimelist": null, "animeplanet": null, "anidb": null, "animenewsnetwork": null}, {"otakotaku": 2278, "title": "Mobile Suit Gundam: Cucuruz Doan's Island", "myanimelist": null, "animeplanet": null, "anidb": null, "animenewsnetwork": null}, {"otakotaku": 2298, "title": "Mobile Suit Gundam: Hathaway's Flash", "myanimelist": null, "animeplanet": null, "anidb": null, "animenewsnetwork": null}, {"otakotaku": 568, "title": "Mobile Suit Gundam: Iron-Blooded Orphans", "myanimelist": null, "animeplanet": null, "anidb": null, "animenewsnetwork": null}, {"otakotaku": 2713, "title": "Monogatari Series: Off & Monster Season", "myanimelist": null, "animeplanet": null, "anidb": null, "animenewsnetwork": null}, {"otakotaku": 806, "title": "Monster Strike Anime", "myanimelist": null, "animeplanet": null, "anidb": null, "animenewsnetwork": null}, {"otakotaku": 622, "title": "Musaigen no Phantom World: Mizutama no Kiseki", "myanimelist": null, "animeplanet": null, "anidb": null, "animenewsnetwork": null}, {"otakotaku": 1181, "title": "Mushishi Zoku Shou Season 2", "myanimelist": null, "animeplanet": null, "anidb": null, "animenewsnetwork": null}, {"otakotaku": 2299, "title": "Mushoku Tensei II: Isekai Ittara Honki Dasu", "myanimelist": null, "animeplanet": null, "anidb": null, "animenewsnetwork": null}, {"otakotaku": 2702, "title": "Mushoku Tensei II: Isekai Ittara Honki Dasu Part 2", "myanimelist": null, "animeplanet": null, "anidb": null, "animenewsnetwork": null}, {"otakotaku": 2040, "title": "Muteking the Dancing Hero", "myanimelist": null, "animeplanet": null, "anidb": null, "animenewsnetwork": null}, {"otakotaku": 2775, "title": "Na Nare Hana Nare", "myanimelist": null, "animeplanet": null, "anidb": null, "animenewsnetwork": null}, {"otakotaku": 739, "title": "Nanbaka 2", "myanimelist": null, "animeplanet": null, "anidb": null, "animenewsnetwork": null}, {"otakotaku": 702, "title": "Nanbaka: Shusseki Bangou no Tsuita Baka-tachi!", "myanimelist": null, "animeplanet": null, "anidb": null, "animenewsnetwork": null}, {"otakotaku": 367, "title": "New Game!", "myanimelist": null, "animeplanet": null, "anidb": null, "animenewsnetwork": null}, {"otakotaku": 783, "title": "New Game!!", "myanimelist": null, "animeplanet": null, "anidb": null, "animenewsnetwork": null}, {"otakotaku": 2854, "title": "NieR:Automata Ver1.1a Part 2", "myanimelist": null, "animeplanet": null, "anidb": null, "animenewsnetwork": null}, {"otakotaku": 1914, "title": "Night Head 2041", "myanimelist": null, "animeplanet": null, "anidb": null, "animenewsnetwork": null}, {"otakotaku": 2506, "title": "Nijiyon Animation", "myanimelist": null, "animeplanet": null, "anidb": null, "animenewsnetwork": null}, {"otakotaku": 2743, "title": "Nijiyon Animation 2", "myanimelist": null, "animeplanet": null, "anidb": null, "animenewsnetwork": null}, {"otakotaku": 1115, "title": "Non Non Biyori Movie: Vacation", "myanimelist": null, "animeplanet": null, "anidb": null, "animenewsnetwork": null}, {"otakotaku": 1889, "title": "Odd Taxi", "myanimelist": null, "animeplanet": null, "anidb": null, "animenewsnetwork": null}, {"otakotaku": 2270, "title": "Odd Taxi Movie: In the Woods", "myanimelist": null, "animeplanet": null, "anidb": null, "animenewsnetwork": null}, {"otakotaku": 1641, "title": "One Piece Movie 14: Stampede", "myanimelist": null, "animeplanet": null, "anidb": null, "animenewsnetwork": null}, {"otakotaku": 2420, "title": "One Punch Man 3", "myanimelist": null, "animeplanet": null, "anidb": null, "animenewsnetwork": null}, {"otakotaku": 586, "title": "One Punch Man Season 2", "myanimelist": null, "animeplanet": null, "anidb": null, "animenewsnetwork": null}, {"otakotaku": 694, "title": "Onihei", "myanimelist": null, "animeplanet": null, "anidb": null, "animenewsnetwork": null}, {"otakotaku": 2274, "title": "Onipan!", "myanimelist": null, "animeplanet": null, "anidb": null, "animenewsnetwork": null}, {"otakotaku": 2290, "title": "Ookami to Koushinryou: Merchant Meets the Wise Wolf", "myanimelist": null, "animeplanet": null, "anidb": null, "animenewsnetwork": null}, {"otakotaku": 2021, "title": "Orient", "myanimelist": null, "animeplanet": null, "anidb": null, "animenewsnetwork": null}, {"otakotaku": 2325, "title": "Orient: Awajishima Gekitou-hen", "myanimelist": null, "animeplanet": null, "anidb": null, "animenewsnetwork": null}, {"otakotaku": 1320, "title": "Osake wa Fuufu ni Natte kara: Yuzu Atsukan", "myanimelist": null, "animeplanet": null, "anidb": null, "animenewsnetwork": null}, {"otakotaku": 856, "title": "Osomatsu-san Season 2", "myanimelist": null, "animeplanet": null, "anidb": null, "animenewsnetwork": null}, {"otakotaku": 1674, "title": "Otome Game no Hametsu Flag shika Nai Akuyaku Reijou ni Tensei shiteshimatta...", "myanimelist": null, "animeplanet": null, "anidb": null, "animenewsnetwork": null}, {"otakotaku": 1902, "title": "Otome Game no Hametsu Flag shika Nai Akuyaku Reijou ni Tensei shiteshimatta... X", "myanimelist": null, "animeplanet": null, "anidb": null, "animenewsnetwork": null}, {"otakotaku": 1854, "title": "Otona no Bouguya-san Season 2", "myanimelist": null, "animeplanet": null, "anidb": null, "animenewsnetwork": null}, {"otakotaku": 602, "title": "Overlord Movie 1: Fushisha no Ou", "myanimelist": null, "animeplanet": null, "anidb": null, "animenewsnetwork": null}, {"otakotaku": 707, "title": "Overlord Movie 2: Shikkoku no Eiyuu", "myanimelist": null, "animeplanet": null, "anidb": null, "animenewsnetwork": null}, {"otakotaku": 2789, "title": "Overlord Movie 3: Sei Oukoku-hen", "myanimelist": null, "animeplanet": null, "anidb": null, "animenewsnetwork": null}, {"otakotaku": 2584, "title": "Overtake!", "myanimelist": null, "animeplanet": null, "anidb": null, "animenewsnetwork": null}, {"otakotaku": 801, "title": "Owarimonogatari Season 2", "myanimelist": null, "animeplanet": null, "anidb": null, "animenewsnetwork": null}, {"otakotaku": 958, "title": "Peace Maker Kurogane Movie 1: Omou Michi", "myanimelist": null, "animeplanet": null, "anidb": null, "animenewsnetwork": null}, {"otakotaku": 482, "title": "Persona 4 the Animation", "myanimelist": null, "animeplanet": null, "anidb": null, "animenewsnetwork": null}, {"otakotaku": 1600, "title": "Pet", "myanimelist": null, "animeplanet": null, "anidb": null, "animenewsnetwork": null}, {"otakotaku": 1655, "title": "Princess Principal: Crown Handler Movie 1", "myanimelist": null, "animeplanet": null, "anidb": null, "animenewsnetwork": null}, {"otakotaku": 1991, "title": "Princess Principal: Crown Handler Movie 2", "myanimelist": null, "animeplanet": null, "anidb": null, "animenewsnetwork": null}, {"otakotaku": 2520, "title": "Princess Principal: Crown Handler Movie 3", "myanimelist": null, "animeplanet": null, "anidb": null, "animenewsnetwork": null}, {"otakotaku": 32, "title": "Prison School", "myanimelist": null, "animeplanet": null, "anidb": null, "animenewsnetwork": null}, {"otakotaku": 1835, "title": "Project Scard: Praeter no Kizu", "myanimelist": null, "animeplanet": null, "anidb": null, "animenewsnetwork": null}, {"otakotaku": 2904, "title": "Project Sekai Movie: Kowareta Sekai to Utaenai Miku", "myanimelist": null, "animeplanet": null, "anidb": null, "animenewsnetwork": null}, {"otakotaku": 1470, "title": "Promare", "myanimelist": null, "animeplanet": null, "anidb": null, "animenewsnetwork": null}, {"otakotaku": 183, "title": "Psycho-Pass", "myanimelist": null, "animeplanet": null, "anidb": null, "animenewsnetwork": null}, {"otakotaku": 184, "title": "Psycho-Pass 2", "myanimelist": null, "animeplanet": null, "anidb": null, "animenewsnetwork": null}, {"otakotaku": 1523, "title": "Psycho-Pass 3", "myanimelist": null, "animeplanet": null, "anidb": null, "animenewsnetwork": null}, {"otakotaku": 1730, "title": "Psycho-Pass 3: First Inspector", "myanimelist": null, "animeplanet": null, "anidb": null, "animenewsnetwork": null}, {"otakotaku": 186, "title": "Psycho-Pass Movie", "myanimelist": null, "animeplanet": null, "anidb": null, "animenewsnetwork": null}, {"otakotaku": 2528, "title": "Psycho-Pass Movie: Providence", "myanimelist": null, "animeplanet": null, "anidb": null, "animenewsnetwork": null}, {"otakotaku": 1357, "title": "Psycho-Pass: Sinners of the System Case.1 - Tsumi to Batsu", "myanimelist": null, "animeplanet": null, "anidb": null, "animenewsnetwork": null}, {"otakotaku": 1358, "title": "Psycho-Pass: Sinners of the System Case.2 - First Guardian", "myanimelist": null, "animeplanet": null, "anidb": null, "animenewsnetwork": null}, {"otakotaku": 1359, "title": "Psycho-Pass: Sinners of the System Case.3 - Onshuu no Kanata ni\uff3f\uff3f", "myanimelist": null, "animeplanet": null, "anidb": null, "animenewsnetwork": null}, {"otakotaku": 1476, "title": "Punch Line", "myanimelist": null, "animeplanet": null, "anidb": null, "animenewsnetwork": null}, {"otakotaku": 1960, "title": "Puraore! Pride of Orange", "myanimelist": null, "animeplanet": null, "anidb": null, "animenewsnetwork": null}, {"otakotaku": 1235, "title": "Radiant", "myanimelist": null, "animeplanet": null, "anidb": null, "animenewsnetwork": null}, {"otakotaku": 1633, "title": "Radiant Season 2", "myanimelist": null, "animeplanet": null, "anidb": null, "animenewsnetwork": null}, {"otakotaku": 1948, "title": "Re-Main", "myanimelist": null, "animeplanet": null, "anidb": null, "animenewsnetwork": null}, {"otakotaku": 456, "title": "Re:Zero kara Hajimeru Break Time", "myanimelist": null, "animeplanet": null, "anidb": null, "animenewsnetwork": null}, {"otakotaku": 2494, "title": "Revenger", "myanimelist": null, "animeplanet": null, "anidb": null, "animenewsnetwork": null}, {"otakotaku": 2103, "title": "Rikei ga Koi ni Ochita no de Shoumei shitemita. Heart", "myanimelist": null, "animeplanet": null, "anidb": null, "animenewsnetwork": null}, {"otakotaku": 2692, "title": "Rinkai!", "myanimelist": null, "animeplanet": null, "anidb": null, "animenewsnetwork": null}, {"otakotaku": 949, "title": "Road to You", "myanimelist": null, "animeplanet": null, "anidb": null, "animenewsnetwork": null}, {"otakotaku": 126, "title": "SKET Dance: Imouto no Nayami ni Nayamu Ani ni Nayamu Imouto to Sono Nakama-tachi", "myanimelist": null, "animeplanet": null, "anidb": null, "animenewsnetwork": null}, {"otakotaku": 1846, "title": "SSSS.Dynazenon", "myanimelist": null, "animeplanet": null, "anidb": null, "animenewsnetwork": null}, {"otakotaku": 1222, "title": "SSSS.Gridman", "myanimelist": null, "animeplanet": null, "anidb": null, "animenewsnetwork": null}, {"otakotaku": 642, "title": "STAR BEAT!: Hoshi no Kodou", "myanimelist": null, "animeplanet": null, "anidb": null, "animenewsnetwork": null}, {"otakotaku": 2090, "title": "Sabikui Bisco", "myanimelist": null, "animeplanet": null, "anidb": null, "animenewsnetwork": null}, {"otakotaku": 1339, "title": "Saiki Kusuo no \u03a8-nan: Kanketsu-hen", "myanimelist": null, "animeplanet": null, "anidb": null, "animenewsnetwork": null}, {"otakotaku": 818, "title": "Saiyuuki Reload Blast", "myanimelist": null, "animeplanet": null, "anidb": null, "animenewsnetwork": null}, {"otakotaku": 2186, "title": "Saiyuuki Reload: Zeroin", "myanimelist": null, "animeplanet": null, "anidb": null, "animenewsnetwork": null}, {"otakotaku": 2848, "title": "Sakamoto Days", "myanimelist": null, "animeplanet": null, "anidb": null, "animenewsnetwork": null}, {"otakotaku": 589, "title": "Sakamoto desu ga? Special", "myanimelist": null, "animeplanet": null, "anidb": null, "animenewsnetwork": null}, {"otakotaku": 1929, "title": "Sakugan", "myanimelist": null, "animeplanet": null, "anidb": null, "animenewsnetwork": null}, {"otakotaku": 670, "title": "Sakurada Reset", "myanimelist": null, "animeplanet": null, "anidb": null, "animenewsnetwork": null}, {"otakotaku": 1988, "title": "Selection Project", "myanimelist": null, "animeplanet": null, "anidb": null, "animenewsnetwork": null}, {"otakotaku": 440, "title": "Servamp", "myanimelist": null, "animeplanet": null, "anidb": null, "animenewsnetwork": null}, {"otakotaku": 1887, "title": "Seven Knights Revolution: Eiyuu no Keishousha", "myanimelist": null, "animeplanet": null, "anidb": null, "animenewsnetwork": null}, {"otakotaku": 1867, "title": "Shadows House", "myanimelist": null, "animeplanet": null, "anidb": null, "animenewsnetwork": null}, {"otakotaku": 2251, "title": "Shadows House Season 2", "myanimelist": null, "animeplanet": null, "anidb": null, "animenewsnetwork": null}, {"otakotaku": 1783, "title": "Shaman King (2021)", "myanimelist": null, "animeplanet": null, "anidb": null, "animenewsnetwork": null}, {"otakotaku": 2651, "title": "Shaman King: Flowers", "myanimelist": null, "animeplanet": null, "anidb": null, "animenewsnetwork": null}, {"otakotaku": 2384, "title": "Shangri-La Frontier: Kusoge Hunter, Kamige ni Idoman to su", "myanimelist": null, "animeplanet": null, "anidb": null, "animenewsnetwork": null}, {"otakotaku": 621, "title": "Shelter", "myanimelist": null, "animeplanet": null, "anidb": null, "animenewsnetwork": null}, {"otakotaku": 1963, "title": "Shikizakura", "myanimelist": null, "animeplanet": null, "anidb": null, "animenewsnetwork": null}, {"otakotaku": 2091, "title": "Shin Tennis no Ouji-sama: U-17 World Cup", "myanimelist": null, "animeplanet": null, "anidb": null, "animenewsnetwork": null}, {"otakotaku": 2805, "title": "Shin Tennis no Ouji-sama: U-17 World Cup Semifinal", "myanimelist": null, "animeplanet": null, "anidb": null, "animenewsnetwork": null}, {"otakotaku": 1571, "title": "Shinchou Yuusha: Kono Yuusha ga Ore Tueee Kuse ni Shinchou Sugiru", "myanimelist": null, "animeplanet": null, "anidb": null, "animenewsnetwork": null}, {"otakotaku": 2252, "title": "Shine Post", "myanimelist": null, "animeplanet": null, "anidb": null, "animenewsnetwork": null}, {"otakotaku": 2385, "title": "Shinigami Bocchan to Kuro Maid Season 2", "myanimelist": null, "animeplanet": null, "anidb": null, "animenewsnetwork": null}, {"otakotaku": 2730, "title": "Shinkalion: Change the World", "myanimelist": null, "animeplanet": null, "anidb": null, "animenewsnetwork": null}, {"otakotaku": 1896, "title": "Shinkansen Henkei Robo Shinkalion The Animation", "myanimelist": null, "animeplanet": null, "anidb": null, "animenewsnetwork": null}, {"otakotaku": 672, "title": "Shinmai Maou no Testament: Toujou Basara no Hard Sweet na Nichijou", "myanimelist": null, "animeplanet": null, "anidb": null, "animenewsnetwork": null}, {"otakotaku": 315, "title": "Shirobako", "myanimelist": null, "animeplanet": null, "anidb": null, "animenewsnetwork": null}, {"otakotaku": 1593, "title": "Shirobako Movie", "myanimelist": null, "animeplanet": null, "anidb": null, "animenewsnetwork": null}, {"otakotaku": 1605, "title": "Shironeko Project: Zero Chronicle", "myanimelist": null, "animeplanet": null, "anidb": null, "animenewsnetwork": null}, {"otakotaku": 479, "title": "Shoujo-tachi wa Kouya wo Mezasu: Iubeki Monokashira", "myanimelist": null, "animeplanet": null, "anidb": null, "animenewsnetwork": null}, {"otakotaku": 2459, "title": "Shy", "myanimelist": null, "animeplanet": null, "anidb": null, "animenewsnetwork": null}, {"otakotaku": 2762, "title": "Shy Season 2", "myanimelist": null, "animeplanet": null, "anidb": null, "animenewsnetwork": null}, {"otakotaku": 50, "title": "Sket Dance", "myanimelist": null, "animeplanet": null, "anidb": null, "animenewsnetwork": null}, {"otakotaku": 911, "title": "SoniAni: Super Sonico The Animation", "myanimelist": null, "animeplanet": null, "anidb": null, "animenewsnetwork": null}, {"otakotaku": 2441, "title": "Sono Bisque Doll wa Koi wo Suru Season 2", "myanimelist": null, "animeplanet": null, "anidb": null, "animenewsnetwork": null}, {"otakotaku": 2172, "title": "Sorairo Utility (TV Special)", "myanimelist": null, "animeplanet": null, "anidb": null, "animenewsnetwork": null}, {"otakotaku": 2323, "title": "Spriggan (ONA)", "myanimelist": null, "animeplanet": null, "anidb": null, "animenewsnetwork": null}, {"otakotaku": 2115, "title": "Spy x Family", "myanimelist": null, "animeplanet": null, "anidb": null, "animenewsnetwork": null}, {"otakotaku": 2569, "title": "Spy x Family Movie: Code: White", "myanimelist": null, "animeplanet": null, "anidb": null, "animenewsnetwork": null}, {"otakotaku": 2374, "title": "Spy x Family Part 2", "myanimelist": null, "animeplanet": null, "anidb": null, "animenewsnetwork": null}, {"otakotaku": 2596, "title": "Spy x Family Season 2", "myanimelist": null, "animeplanet": null, "anidb": null, "animenewsnetwork": null}, {"otakotaku": 1413, "title": "Steins;Gate 0: Kesshou Takei no Valentine - Bittersweet Intermedio", "myanimelist": null, "animeplanet": null, "anidb": null, "animenewsnetwork": null}, {"otakotaku": 584, "title": "Strike the Blood: Valkyria no Oukoku-hen", "myanimelist": null, "animeplanet": null, "anidb": null, "animenewsnetwork": null}, {"otakotaku": 123, "title": "Subete ga F ni Naru", "myanimelist": null, "animeplanet": null, "anidb": null, "animenewsnetwork": null}, {"otakotaku": 2585, "title": "Sugar Apple Fairy Tale Part 2", "myanimelist": null, "animeplanet": null, "anidb": null, "animenewsnetwork": null}, {"otakotaku": 2001, "title": "Summer Ghost", "myanimelist": null, "animeplanet": null, "anidb": null, "animenewsnetwork": null}, {"otakotaku": 1985, "title": "Sword Art Online: Progressive Movie - Hoshi Naki Yoru no Aria", "myanimelist": null, "animeplanet": null, "anidb": null, "animenewsnetwork": null}, {"otakotaku": 2443, "title": "Synduality: Noir", "myanimelist": null, "animeplanet": null, "anidb": null, "animenewsnetwork": null}, {"otakotaku": 2686, "title": "Synduality: Noir Part 2", "myanimelist": null, "animeplanet": null, "anidb": null, "animenewsnetwork": null}, {"otakotaku": 2051, "title": "Tabi-Hani", "myanimelist": null, "animeplanet": null, "anidb": null, "animenewsnetwork": null}, {"otakotaku": 1068, "title": "Tachibanakan Triangle", "myanimelist": null, "animeplanet": null, "anidb": null, "animenewsnetwork": null}, {"otakotaku": 1811, "title": "Taisou Zamurai", "myanimelist": null, "animeplanet": null, "anidb": null, "animenewsnetwork": null}, {"otakotaku": 1974, "title": "Takt Op. Destiny", "myanimelist": null, "animeplanet": null, "anidb": null, "animenewsnetwork": null}, {"otakotaku": 354, "title": "Tales of Zestiria the Cross", "myanimelist": null, "animeplanet": null, "anidb": null, "animenewsnetwork": null}, {"otakotaku": 451, "title": "Tamako Market Specials", "myanimelist": null, "animeplanet": null, "anidb": null, "animenewsnetwork": null}, {"otakotaku": 2864, "title": "Tasokare Hotel", "myanimelist": null, "animeplanet": null, "anidb": null, "animenewsnetwork": null}, {"otakotaku": 2302, "title": "Technoroid: Overmind", "myanimelist": null, "animeplanet": null, "anidb": null, "animenewsnetwork": null}, {"otakotaku": 1196, "title": "Tensei shitara Slime Datta Ken", "myanimelist": null, "animeplanet": null, "anidb": null, "animenewsnetwork": null}, {"otakotaku": 1539, "title": "Tensei shitara Slime Datta Ken Season 2", "myanimelist": null, "animeplanet": null, "anidb": null, "animenewsnetwork": null}, {"otakotaku": 1904, "title": "Tensei shitara Slime Datta Ken Season 2 Part 2", "myanimelist": null, "animeplanet": null, "anidb": null, "animenewsnetwork": null}, {"otakotaku": 2017, "title": "Tesla Note", "myanimelist": null, "animeplanet": null, "anidb": null, "animenewsnetwork": null}, {"otakotaku": 710, "title": "The Ancient Silat", "myanimelist": null, "animeplanet": null, "anidb": null, "animenewsnetwork": null}, {"otakotaku": 2484, "title": "The First Slam Dunk", "myanimelist": null, "animeplanet": null, "anidb": null, "animenewsnetwork": null}, {"otakotaku": 2491, "title": "The IDOLM@STER Cinderella Girls: U149", "myanimelist": null, "animeplanet": null, "anidb": null, "animenewsnetwork": null}, {"otakotaku": 257, "title": "The Law of Ueki", "myanimelist": null, "animeplanet": null, "anidb": null, "animenewsnetwork": null}, {"otakotaku": 2510, "title": "The Marginal Service", "myanimelist": null, "animeplanet": null, "anidb": null, "animenewsnetwork": null}, {"otakotaku": 2732, "title": "The New Gate", "myanimelist": null, "animeplanet": null, "anidb": null, "animenewsnetwork": null}, {"otakotaku": 2529, "title": "The iDOLM@STER Million Live!", "myanimelist": null, "animeplanet": null, "anidb": null, "animenewsnetwork": null}, {"otakotaku": 2723, "title": "The iDOLM@STER Shiny Colors", "myanimelist": null, "animeplanet": null, "anidb": null, "animenewsnetwork": null}, {"otakotaku": 2832, "title": "The iDOLM@STER Shiny Colors 2nd Season", "myanimelist": null, "animeplanet": null, "anidb": null, "animenewsnetwork": null}, {"otakotaku": 2019, "title": "Tiger & Bunny", "myanimelist": null, "animeplanet": null, "anidb": null, "animenewsnetwork": null}, {"otakotaku": 2148, "title": "Tiger & Bunny 2", "myanimelist": null, "animeplanet": null, "anidb": null, "animenewsnetwork": null}, {"otakotaku": 1158, "title": "To Be Heroine", "myanimelist": null, "animeplanet": null, "anidb": null, "animenewsnetwork": null}, {"otakotaku": 1837, "title": "Tokyo Babylon 2021", "myanimelist": null, "animeplanet": null, "anidb": null, "animenewsnetwork": null}, {"otakotaku": 1199, "title": "Tokyo Ghoul:re Season 2", "myanimelist": null, "animeplanet": null, "anidb": null, "animenewsnetwork": null}, {"otakotaku": 537, "title": "Trickster: Edogawa Ranpo \"Shounen Tanteidan\" yori", "myanimelist": null, "animeplanet": null, "anidb": null, "animenewsnetwork": null}, {"otakotaku": 2379, "title": "Trigun Stampede", "myanimelist": null, "animeplanet": null, "anidb": null, "animenewsnetwork": null}, {"otakotaku": 2802, "title": "Trillion Game", "myanimelist": null, "animeplanet": null, "anidb": null, "animenewsnetwork": null}, {"otakotaku": 633, "title": "Trinity Seven", "myanimelist": null, "animeplanet": null, "anidb": null, "animenewsnetwork": null}, {"otakotaku": 687, "title": "Trinity Seven Movie 1: Eternity Library to Alchemic Girl", "myanimelist": null, "animeplanet": null, "anidb": null, "animenewsnetwork": null}, {"otakotaku": 1224, "title": "Trinity Seven Movie 2: Heaven\u2019s Library", "myanimelist": null, "animeplanet": null, "anidb": null, "animenewsnetwork": null}, {"otakotaku": 894, "title": "Tsukipro The Animation", "myanimelist": null, "animeplanet": null, "anidb": null, "animenewsnetwork": null}, {"otakotaku": 1949, "title": "Tsukipro The Animation 2", "myanimelist": null, "animeplanet": null, "anidb": null, "animenewsnetwork": null}, {"otakotaku": 471, "title": "Tsukiuta. The Animation", "myanimelist": null, "animeplanet": null, "anidb": null, "animenewsnetwork": null}, {"otakotaku": 1697, "title": "Tsukiuta. The Animation 2", "myanimelist": null, "animeplanet": null, "anidb": null, "animenewsnetwork": null}, {"otakotaku": 2292, "title": "Tsurune: Hajimari no Issha", "myanimelist": null, "animeplanet": null, "anidb": null, "animenewsnetwork": null}, {"otakotaku": 895, "title": "Two Car", "myanimelist": null, "animeplanet": null, "anidb": null, "animenewsnetwork": null}, {"otakotaku": 837, "title": "UQ Holder!: Mahou Sensei Negima! 2", "myanimelist": null, "animeplanet": null, "anidb": null, "animenewsnetwork": null}, {"otakotaku": 1477, "title": "Ultraman", "myanimelist": null, "animeplanet": null, "anidb": null, "animenewsnetwork": null}, {"otakotaku": 2250, "title": "Ultraman Season 2", "myanimelist": null, "animeplanet": null, "anidb": null, "animenewsnetwork": null}, {"otakotaku": 2511, "title": "Uma Musume: Pretty Derby - Road to the Top", "myanimelist": null, "animeplanet": null, "anidb": null, "animenewsnetwork": null}, {"otakotaku": 1865, "title": "Uma Musume: Pretty Derby Season 2", "myanimelist": null, "animeplanet": null, "anidb": null, "animenewsnetwork": null}, {"otakotaku": 2544, "title": "Uma Musume: Pretty Derby Season 3", "myanimelist": null, "animeplanet": null, "anidb": null, "animenewsnetwork": null}, {"otakotaku": 2534, "title": "Undead Unluck", "myanimelist": null, "animeplanet": null, "anidb": null, "animenewsnetwork": null}, {"otakotaku": 2618, "title": "Under Ninja", "myanimelist": null, "animeplanet": null, "anidb": null, "animenewsnetwork": null}, {"otakotaku": 882, "title": "Urahara", "myanimelist": null, "animeplanet": null, "anidb": null, "animenewsnetwork": null}, {"otakotaku": 2671, "title": "Urusei Yatsura Season 2", "myanimelist": null, "animeplanet": null, "anidb": null, "animenewsnetwork": null}, {"otakotaku": 1652, "title": "Uta no\u2606Prince-sama\u266a Maji Love Kingdom Movie", "myanimelist": null, "animeplanet": null, "anidb": null, "animenewsnetwork": null}, {"otakotaku": 2095, "title": "Vanitas no Karte Part 2", "myanimelist": null, "animeplanet": null, "anidb": null, "animenewsnetwork": null}, {"otakotaku": 2423, "title": "Vazzrock The Animation", "myanimelist": null, "animeplanet": null, "anidb": null, "animenewsnetwork": null}, {"otakotaku": 1280, "title": "Vinland Saga", "myanimelist": null, "animeplanet": null, "anidb": null, "animenewsnetwork": null}, {"otakotaku": 2405, "title": "Vinland Saga Season 2", "myanimelist": null, "animeplanet": null, "anidb": null, "animenewsnetwork": null}, {"otakotaku": 1954, "title": "Visual Prison", "myanimelist": null, "animeplanet": null, "anidb": null, "animenewsnetwork": null}, {"otakotaku": 1708, "title": "Vlad Love", "myanimelist": null, "animeplanet": null, "anidb": null, "animenewsnetwork": null}, {"otakotaku": 1841, "title": "WIXOSS Diva(A)Live", "myanimelist": null, "animeplanet": null, "anidb": null, "animenewsnetwork": null}, {"otakotaku": 2714, "title": "Wind Breaker", "myanimelist": null, "animeplanet": null, "anidb": null, "animenewsnetwork": null}, {"otakotaku": 1855, "title": "Wonder Egg Priority", "myanimelist": null, "animeplanet": null, "anidb": null, "animenewsnetwork": null}, {"otakotaku": 1979, "title": "Wonder Egg Priority Special", "myanimelist": null, "animeplanet": null, "anidb": null, "animenewsnetwork": null}, {"otakotaku": 1828, "title": "World Trigger Season 2", "myanimelist": null, "animeplanet": null, "anidb": null, "animenewsnetwork": null}, {"otakotaku": 1628, "title": "XL Joushi.", "myanimelist": null, "animeplanet": null, "anidb": null, "animenewsnetwork": null}, {"otakotaku": 1, "title": "Yahari Ore no Seishun Love Comedy wa Machigatteiru", "myanimelist": null, "animeplanet": null, "anidb": null, "animenewsnetwork": null}, {"otakotaku": 182, "title": "Yahari Ore no Seishun Love Comedy wa Machigatteiru OVA", "myanimelist": null, "animeplanet": null, "anidb": null, "animenewsnetwork": null}, {"otakotaku": 935, "title": "Yama no Susume: Second Season", "myanimelist": null, "animeplanet": null, "anidb": null, "animenewsnetwork": null}, {"otakotaku": 1684, "title": "Yatogame-chan Kansatsu Nikki Nisatsume", "myanimelist": null, "animeplanet": null, "anidb": null, "animenewsnetwork": null}, {"otakotaku": 1829, "title": "Yatogame-chan Kansatsu Nikki Sansatsume", "myanimelist": null, "animeplanet": null, "anidb": null, "animenewsnetwork": null}, {"otakotaku": 641, "title": "Yes! BanG_Dream!", "myanimelist": null, "animeplanet": null, "anidb": null, "animenewsnetwork": null}, {"otakotaku": 1981, "title": "Yoshimaho", "myanimelist": null, "animeplanet": null, "anidb": null, "animenewsnetwork": null}, {"otakotaku": 234, "title": "Yowamushi Pedal: GRANDE ROAD", "myanimelist": null, "animeplanet": null, "anidb": null, "animenewsnetwork": null}, {"otakotaku": 2326, "title": "Yurei Deco", "myanimelist": null, "animeplanet": null, "anidb": null, "animenewsnetwork": null}, {"otakotaku": 555, "title": "Yuri!!! on Ice", "myanimelist": null, "animeplanet": null, "anidb": null, "animenewsnetwork": null}, {"otakotaku": 1872, "title": "Yuukoku no Moriarty Season 2", "myanimelist": null, "animeplanet": null, "anidb": null, "animenewsnetwork": null}, {"otakotaku": 1147, "title": "Yuu\u2606Yuu\u2606Hakusho: Two Shots/Noru ka Soru ka", "myanimelist": null, "animeplanet": null, "anidb": null, "animenewsnetwork": null}, {"otakotaku": 2258, "title": "Yu\u2606Gi\u2606Oh!: Go Rush!!", "myanimelist": null, "animeplanet": null, "anidb": null, "animenewsnetwork": null}, {"otakotaku": 2801, "title": "Zenshuu.", "myanimelist": null, "animeplanet": null, "anidb": null, "animenewsnetwork": null}, {"otakotaku": 1293, "title": "Zombieland Saga", "myanimelist": null, "animeplanet": null, "anidb": null, "animenewsnetwork": null}, {"otakotaku": 1610, "title": "Zombieland Saga: Revenge", "myanimelist": null, "animeplanet": null, "anidb": null, "animenewsnetwork": null}]